pycifstar/__init__.py
pycifstar/data.py
pycifstar/global_.py
pycifstar/item.py
pycifstar/items.py
pycifstar/loop.py
pystar/__init__.py
pystar/data.py
pystar/global_.py
pystar/item.py
pystar/items.py
pystar/loop.py
pycifstar-0.2.8.dist-info/LICENSE
pycifstar-0.2.8.dist-info/METADATA
pycifstar-0.2.8.dist-info/WHEEL
pycifstar-0.2.8.dist-info/top_level.txt
pycifstar-0.2.8.dist-info/RECORD
