Metadata-Version: 2.1
Name: pycifstar
Version: 0.2.8
Summary: PyCifStar is  a class library for  data manipulation  provided in the CIF/STAR File.
Home-page: https://github.com/ikibalin/pycifstar
Author: Iurii Kibalin
Author-email: yurikibalin@outlook.com
License: MIT License
Keywords: STAR,CIF
Platform: UNKNOWN
Classifier: Programming Language :: Python :: 3
Classifier: Programming Language :: Python :: 3.5
Classifier: Programming Language :: Python :: 3.6
Classifier: Programming Language :: Python :: 3.7
Classifier: Operating System :: OS Independent
